ots/__init__.py
ots/__main__.py
ots/_version.py
ots/ots-sanitize.exe
opentype_sanitizer-9.2.0.dist-info/LICENSE
opentype_sanitizer-9.2.0.dist-info/METADATA
opentype_sanitizer-9.2.0.dist-info/WHEEL
opentype_sanitizer-9.2.0.dist-info/top_level.txt
opentype_sanitizer-9.2.0.dist-info/RECORD
