Metadata-Version: 2.1
Name: opentype-sanitizer
Version: 9.2.0
Summary: Python wrapper for the OpenType Sanitizer
Home-page: https://github.com/googlefonts/ots-python
Author: Cosimo Lupo
Author-email: cosimo@anthrotype.com
License: OpenSource, BSD-style
Platform: posix
Platform: nt
Classifier: Development Status :: 5 - Production/Stable
Classifier: Environment :: Console
Classifier: Environment :: Other Environment
Classifier: Intended Audience :: Developers
Classifier: Intended Audience :: End Users/Desktop
Classifier: License :: OSI Approved :: BSD License
Classifier: Natural Language :: English
Classifier: Operating System :: OS Independent
Classifier: Programming Language :: Python
Classifier: Programming Language :: Python :: 2
Classifier: Programming Language :: Python :: 3
Classifier: Topic :: Text Processing :: Fonts
Classifier: Topic :: Multimedia :: Graphics
License-File: LICENSE
Provides-Extra: testing
Requires-Dist: pytest; extra == "testing"
